xath/__init__.py
xath/_modidx.py
xath/base.py
xath/data.py
xath/expt.py
xath/leaf.py
xath/name.py
xath/mxns/__init__.py
xath/mxns/data.py
xath/mxns/expt.py
xath/mxns/kind.py
xath/mxns/plib.py
xath/mxns/reqr.py
xath/plib/__init__.py
xath/plib/lib.py
xath/plib/psx.py
xath/plib/wdx.py
xath-0.0.6.dist-info/LICENSE
xath-0.0.6.dist-info/METADATA
xath-0.0.6.dist-info/WHEEL
xath-0.0.6.dist-info/entry_points.txt
xath-0.0.6.dist-info/top_level.txt
xath-0.0.6.dist-info/RECORD
