Metadata-Version: 2.1
Name: xath
Version: 0.0.6
Summary: structured directories
Home-page: https://github.com/dsm-72/xath
Author: dsm-72
Author-email: sumner.magruder@yale.edu
License: Apache Software License 2.0
Classifier: Development Status :: 4 - Beta
Classifier: Intended Audience :: Developers
Classifier: Natural Language :: English
Classifier: Programming Language :: Python :: 3.11
Classifier: License :: OSI Approved :: Apache Software License
Requires-Python: >=3.11
License-File: LICENSE
Requires-Dist: atyp
Requires-Dist: regsyn
Requires-Dist: ispec
Requires-Dist: pstr
Requires-Dist: psrc
Requires-Dist: chck
Requires-Dist: urllib3
Provides-Extra: dev
